wordle/__init__.py
wordle/analysis/__init__.py
wordle/core/__init__.py
wordle/core/gameplay.py
wordle/core/result.py
wordle/guess/__init__.py
wordle/guess/base.py
wordle/guess/exhaustive.py
wordle/guess/frequency.py
wordle/guess/random.py
wordle/lists/.gitignore
wordle/lists/__init__.py
wordle/lists/equations-6.txt
wordle/lists/equations-7.txt
wordle/lists/equations-8.txt
wordle/lists/expressions-5.txt
wordle/lists/expressions-6.txt
wordle/lists/mathler.py
wordle/lists/wordle-answers.txt
wordle/lists/wordle-guesses.txt
wordle/play/__init__.py
wordle/play/mathler.py
wordle/play/wordle.py
wordle/tests/__init__.py
wordle/tests/test_gameplay.py
wordle/tests/test_result.py
wordle_utils-0.3.0.dist-info/METADATA
wordle_utils-0.3.0.dist-info/WHEEL
wordle_utils-0.3.0.dist-info/entry_points.txt
wordle_utils-0.3.0.dist-info/top_level.txt
wordle_utils-0.3.0.dist-info/RECORD
