Metadata-Version: 2.1
Name: wordle-utils
Version: 0.3.0
Summary: Helper functions, word lists, and analysis tools for Wordle and other Wordle variants.
Home-page: https://github.com/mattdodge/wordle-utils
Author: Matt Dodge
Author-email: wordle@mattdodge.codes
License: UNKNOWN
Platform: UNKNOWN
Classifier: Programming Language :: Python :: 3
Classifier: License :: OSI Approved :: MIT License
Classifier: Operating System :: OS Independent
